jupyter_ai_debugger/__init__.py
jupyter_ai_debugger/config.py
jupyter_ai_debugger/core.py
jupyter_ai_debugger-0.1.0.dist-info/licenses/LICENSE
jupyter_ai_debugger-0.1.0.dist-info/METADATA
jupyter_ai_debugger-0.1.0.dist-info/WHEEL
jupyter_ai_debugger-0.1.0.dist-info/top_level.txt
jupyter_ai_debugger-0.1.0.dist-info/RECORD
