Metadata-Version: 2.4
Name: jupyter-ai-debugger
Version: 0.1.0
Summary: AI-assisted error debugger with OpenRouter model fallback for Jupyter.
Author: Your Name
License-Expression: MIT
Project-URL: Homepage, https://github.com/yourname/jupyter_ai_debugger
License-File: LICENSE
Requires-Dist: requests
Requires-Dist: ipython
Dynamic: license-file
